[{"path":"/SC-Bridge/sc-bridge","title":"Overview","count":19,"uniques":10},{"path":"/SC-Bridge/sc-bridge/issues","title":"/issues","count":3,"uniques":3},{"path":"/SC-Bridge/sc-bridge/branches","title":"/branches","count":3,"uniques":1},{"path":"/SC-Bridge/sc-bridge/issues/133","title":"/issues/133","count":3,"uniques":1},{"path":"/SC-Bridge/sc-bridge/branches/yours","title":"/branches/yours","count":1,"uniques":1},{"path":"/SC-Bridge/sc-bridge/issues/139","title":"/issues/139","count":1,"uniques":1},{"path":"/gavinmcfall/fleet-manager","title":"Overview","count":1,"uniques":1},{"path":"/gavinmcfall/fleet-manager/blob/main/docker-compose.yml","title":"/blob/main/docker-compose.yml","count":1,"uniques":1}]